waybacksavebulk/__init__.py
waybacksavebulk/requirements.txt
waybacksavebulk/waybacksavebulk.py
waybacksavebulk-1.2.dist-info/METADATA
waybacksavebulk-1.2.dist-info/WHEEL
waybacksavebulk-1.2.dist-info/entry_points.txt
waybacksavebulk-1.2.dist-info/top_level.txt
waybacksavebulk-1.2.dist-info/RECORD
