Metadata-Version: 2.4
Name: waybacksavebulk
Version: 1.2
Summary: A simple script to bulk save URLs to the archive.org Wayback Machine
Author-email: tdebize@mail.com
License-Expression: LGPL-3.0-or-later
Project-URL: Homepage, https://github.com/maaaaz/waybacksavebulk
Keywords: wayback,machine,archive,archive.org,save
Classifier: Topic :: Security
Classifier: Programming Language :: Python :: 3
Requires-Python: >=3
Requires-Dist: waybackpy
Requires-Dist: w3lib
